<?xml version="1.0" encoding="iso-8859-1" ?>
<!DOCTYPE rem:requirementsProject SYSTEM "C:\Program Files (x86)\REM 1.2.2\xml\REM_1_2_2.dtd">
<rem:requirementsProject
xmlns:rem="http://rem.lsi.us.es">
<rem:name>Social Work</rem:name>
<rem:c_requirementsSpecification oid = "CRS-0001">
<rem:name>Documento de Requisitos del Sistema</rem:name>
<rem:version>
<rem:major>1</rem:major>
<rem:minor>0</rem:minor>
<rem:date>
<rem:year>2016</rem:year>
<rem:month>2</rem:month>
<rem:day>20</rem:day>
</rem:date>
</rem:version>
<rem:comments>
Ninguno
</rem:comments>
	 <rem:preparedBy organizations = "ORG-0001 "/>
<rem:organization
 oid = "ORG-0001">
<rem:name>
SK Inc S.A. de C.V.</rem:name>
<rem:version>
<rem:major>1</rem:major>
<rem:minor>0</rem:minor>
<rem:date>
<rem:year>2016</rem:year>
<rem:month>2</rem:month>
<rem:day>20</rem:day>
</rem:date>
</rem:version>
<rem:authors stakeholders ="STK-0001 "/>
<rem:comments>
Ninguno</rem:comments>
<rem:address><rem:tbd/></rem:address>
<rem:telephone>5541364626</rem:telephone>
<rem:fax><rem:tbd/></rem:fax>
</rem:organization>
<rem:stakeholder
 oid = "STK-0001">
<rem:name>
Diego Núñez</rem:name>
<rem:version>
<rem:major>1</rem:major>
<rem:minor>0</rem:minor>
<rem:date>
<rem:year>2016</rem:year>
<rem:month>2</rem:month>
<rem:day>20</rem:day>
</rem:date>
</rem:version>
<rem:comments>
Ninguno</rem:comments>
<rem:stakeholderRole>Líder de Proyecto</rem:stakeholderRole>
<rem:isDeveloper/>
</rem:stakeholder>
<rem:objective
 oid = "OBJ-0001">
<rem:name>
Social Work</rem:name>
<rem:version>
<rem:major>1</rem:major>
<rem:minor>0</rem:minor>
<rem:date>
<rem:year>2016</rem:year>
<rem:month>2</rem:month>
<rem:day>20</rem:day>
</rem:date>
</rem:version>
<rem:authors stakeholders ="STK-0001 "/>
<rem:comments>
Ninguno</rem:comments>
<rem:importance>
<rem:tbd/>
</rem:importance>
<rem:urgency>
<rem:tbd/>
</rem:urgency>
<rem:status>
<rem:tbd/>
</rem:status>
<rem:stability>
<rem:tbd/>
</rem:stability>
<rem:description>
permitir a las personas que se encuentran desempleadas una solución más factible y económica para buscar empleo.</rem:description>
</rem:objective>
<rem:actor
 oid = "ACT-0001">
<rem:name>
Persona Desempleada</rem:name>
<rem:version>
<rem:major>1</rem:major>
<rem:minor>0</rem:minor>
<rem:date>
<rem:year>2016</rem:year>
<rem:month>2</rem:month>
<rem:day>20</rem:day>
</rem:date>
</rem:version>
<rem:authors stakeholders ="STK-0001 "/>
<rem:comments>
Ninguno</rem:comments>
<rem:actorRole>persona que busca empleo</rem:actorRole>
</rem:actor>
<rem:actor
 oid = "ACT-0002">
<rem:name>
Empresa</rem:name>
<rem:version>
<rem:major>1</rem:major>
<rem:minor>0</rem:minor>
<rem:date>
<rem:year>2016</rem:year>
<rem:month>2</rem:month>
<rem:day>20</rem:day>
</rem:date>
</rem:version>
<rem:authors stakeholders ="STK-0001 "/>
<rem:comments>
Ninguno</rem:comments>
<rem:actorRole>persona de área recursos humanos que publica vacantes de empleo</rem:actorRole>
</rem:actor>
<rem:useCase
 oid = "UC-0001">
<rem:name>
Ingresar al Sistema(Persona Desempleada)</rem:name>
<rem:version>
<rem:major>1</rem:major>
<rem:minor>0</rem:minor>
<rem:date>
<rem:year>2016</rem:year>
<rem:month>2</rem:month>
<rem:day>20</rem:day>
</rem:date>
</rem:version>
<rem:authors stakeholders ="STK-0001 "/>
<rem:comments>
Ninguno</rem:comments>
<rem:importance value = "IMV-0003"/>
<rem:urgency value = "URV-0003"/>
<rem:status value = "STV-0003"/>
<rem:stability value = "SBV-0002"/>
<rem:triggeringEvent>
el usuario desea buscar las vacantes de empleo que ofrecen algunas empresas, actualizar su información o revisar el estatus a la vacante que se postuló</rem:triggeringEvent>
<rem:precondition>
Haberse registrado en el apartado &quot;busco empleo&quot; para obtener una cuenta otorgada por el sistema</rem:precondition>
<rem:postcondition>
Se tendrá acceso al sistema</rem:postcondition>
<rem:frequency>
<rem:value>
10
</rem:value>
<rem:timeUnit value = "TUV-0010"/>
</rem:frequency>
<rem:step oid = "STP-0002">
<rem:number>1</rem:number>
<rem:actorAction actor = "ACT-0001">
<rem:description>
selecciona la opción iniciar sesión</rem:description>
</rem:actorAction>
<rem:comments>
</rem:comments>
</rem:step>
<rem:step oid = "STP-0003">
<rem:number>2</rem:number>
<rem:systemAction>
<rem:description>
muestra los campos de usuario y contraseña</rem:description>
</rem:systemAction>
<rem:comments>
Ninguno</rem:comments>
</rem:step>
<rem:step oid = "STP-0004">
<rem:number>3</rem:number>
<rem:actorAction actor = "ACT-0001">
<rem:description>
escribe su nombre de usuario y contraseña</rem:description>
</rem:actorAction>
<rem:comments>
Ninguno</rem:comments>
</rem:step>
<rem:step oid = "STP-0005">
<rem:number>4</rem:number>
<rem:systemAction>
<rem:description>
verifica que el usuario y contraseña ingresados existan en la base de datos</rem:description>
</rem:systemAction>
<rem:stepException oid = "STX-0001">
<rem:condition>
el usuario o contraseña no existen</rem:condition>
<rem:systemAction>
<rem:description>
mostrará un mensaje de error &quot;los datos ingresados no existen&quot;</rem:description>
</rem:systemAction>
<rem:termination value = "TEV-0002"/>
<rem:comments>
regresa al paso 3</rem:comments>
</rem:stepException>
<rem:comments>
Ninguno</rem:comments>
</rem:step>
<rem:step oid = "STP-0007">
<rem:number>5</rem:number>
<rem:systemAction>
<rem:description>
mostrará la pantalla de inicio para el usuario que busca empleo</rem:description>
</rem:systemAction>
<rem:comments>
Ninguno</rem:comments>
</rem:step>
</rem:useCase>
<rem:useCase
 oid = "UC-0002">
<rem:name>
Ingresar al Sistema(Empresa)</rem:name>
<rem:version>
<rem:major>1</rem:major>
<rem:minor>0</rem:minor>
<rem:date>
<rem:year>2016</rem:year>
<rem:month>2</rem:month>
<rem:day>20</rem:day>
</rem:date>
</rem:version>
<rem:authors stakeholders ="STK-0001 "/>
<rem:comments>
Ninguno</rem:comments>
<rem:importance value = "IMV-0003"/>
<rem:urgency value = "URV-0003"/>
<rem:status value = "STV-0003"/>
<rem:stability value = "SBV-0003"/>
<rem:triggeringEvent>
la empresa desea publicar una nueva vacante o actualizar su información</rem:triggeringEvent>
<rem:precondition>
Ninguna</rem:precondition>
<rem:postcondition>
El usuario ingresará a su cuenta</rem:postcondition>
<rem:frequency>
<rem:value>
10
</rem:value>
<rem:timeUnit value = "TUV-0010"/>
</rem:frequency>
<rem:step oid = "STP-0008">
<rem:number>1</rem:number>
<rem:actorAction actor = "ACT-0002">
<rem:description>
selecciona la opción iniciar sesión</rem:description>
</rem:actorAction>
<rem:comments>
Ninguno</rem:comments>
</rem:step>
<rem:step oid = "STP-0009">
<rem:number>2</rem:number>
<rem:systemAction>
<rem:description>
muestra los campos de usuario y contraseña</rem:description>
</rem:systemAction>
<rem:comments>
Ninguno</rem:comments>
</rem:step>
<rem:step oid = "STP-0010">
<rem:number>3</rem:number>
<rem:actorAction actor = "ACT-0002">
<rem:description>
escribe su nombre de usuario y contraseña</rem:description>
</rem:actorAction>
<rem:comments>
Ninguno</rem:comments>
</rem:step>
<rem:step oid = "STP-0011">
<rem:number>4</rem:number>
<rem:systemAction>
<rem:description>
verifica que el usuario y contraseña ingresados existan en la base de datos</rem:description>
</rem:systemAction>
<rem:stepException oid = "STX-0002">
<rem:condition>
el usuario o contraseña no existen</rem:condition>
<rem:systemAction>
<rem:description>
mostrará un mensaje de error &quot;los datos ingresados no existen&quot;</rem:description>
</rem:systemAction>
<rem:termination value = "TEV-0002"/>
<rem:comments>
regresa al paso 3</rem:comments>
</rem:stepException>
<rem:comments>
Ninguno</rem:comments>
</rem:step>
<rem:step oid = "STP-0012">
<rem:number>5</rem:number>
<rem:systemAction>
<rem:description>
mostrará la pantalla de inicio para empresa</rem:description>
</rem:systemAction>
<rem:comments>
Ninguno</rem:comments>
</rem:step>
</rem:useCase>
<rem:useCase
 oid = "UC-0003">
<rem:name>
Registrar PersonaDesemplada</rem:name>
<rem:version>
<rem:major>1</rem:major>
<rem:minor>0</rem:minor>
<rem:date>
<rem:year>2016</rem:year>
<rem:month>2</rem:month>
<rem:day>21</rem:day>
</rem:date>
</rem:version>
<rem:authors stakeholders ="STK-0001 "/>
<rem:comments>
Ninguno</rem:comments>
<rem:importance value = "IMV-0002"/>
<rem:urgency value = "URV-0003"/>
<rem:status value = "STV-0003"/>
<rem:stability value = "SBV-0003"/>
<rem:triggeringEvent>
el usuario desea darse de alta en el sistema para conocer vacantes de empleo que publican algunas empresas</rem:triggeringEvent>
<rem:precondition>
Ninguna</rem:precondition>
<rem:postcondition>
El usuario tendrá una cuenta en el sistema</rem:postcondition>
<rem:frequency>
<rem:value>
10
</rem:value>
<rem:timeUnit value = "TUV-0010"/>
</rem:frequency>
<rem:step oid = "STP-0013">
<rem:number>1</rem:number>
<rem:actorAction actor = "ACT-0001">
<rem:description>
selecciona la opcion registrarse</rem:description>
</rem:actorAction>
<rem:comments>
Ninguno</rem:comments>
</rem:step>
<rem:step oid = "STP-0014">
<rem:number>2</rem:number>
<rem:systemAction>
<rem:description>
muestra los campos que deben llenarse</rem:description>
</rem:systemAction>
<rem:comments>
Ninguno</rem:comments>
</rem:step>
<rem:step oid = "STP-0015">
<rem:number>3</rem:number>
<rem:actorAction actor = "ACT-0001">
<rem:description>
ingresa la información solicitada</rem:description>
</rem:actorAction>
<rem:stepException oid = "STX-0003">
<rem:condition>
falta algún campo por llenar</rem:condition>
<rem:systemAction>
<rem:description>
mostrará un mensaje de error &quot;llene todos los campos&quot;</rem:description>
</rem:systemAction>
<rem:termination value = "TEV-0002"/>
<rem:comments>
regresa al paso 3</rem:comments>
</rem:stepException>
<rem:comments>
Ninguno</rem:comments>
</rem:step>
<rem:step oid = "STP-0016">
<rem:number>4</rem:number>
<rem:systemAction>
<rem:description>
verifica si ya se ha dado de alta este usuario</rem:description>
</rem:systemAction>
<rem:stepException oid = "STX-0004">
<rem:condition>
la información ingresada ya existe en la base de datos</rem:condition>
<rem:systemAction>
<rem:description>
el sistema mostrará un mensaje de error &quot;Esta información ya existe&quot;</rem:description>
</rem:systemAction>
<rem:termination value = "TEV-0002"/>
<rem:comments>
regresa al paso 3</rem:comments>
</rem:stepException>
<rem:comments>
Ninguno</rem:comments>
</rem:step>
<rem:step oid = "STP-0017">
<rem:number>5</rem:number>
<rem:systemAction>
<rem:description>
dará de alta a este usuario</rem:description>
</rem:systemAction>
<rem:comments>
Ninguno</rem:comments>
</rem:step>
<rem:step oid = "STP-0018">
<rem:number>6</rem:number>
<rem:systemAction>
<rem:description>
notificará al usuario que se ha registrado correctamente</rem:description>
</rem:systemAction>
<rem:comments>
Ninguno</rem:comments>
</rem:step>
</rem:useCase>
<rem:useCase
 oid = "UC-0004">
<rem:name>
Registrar Empresa</rem:name>
<rem:version>
<rem:major>1</rem:major>
<rem:minor>0</rem:minor>
<rem:date>
<rem:year>2016</rem:year>
<rem:month>2</rem:month>
<rem:day>21</rem:day>
</rem:date>
</rem:version>
<rem:authors stakeholders ="STK-0001 "/>
<rem:comments>
Ninguno</rem:comments>
<rem:importance value = "IMV-0002"/>
<rem:urgency value = "URV-0003"/>
<rem:status value = "STV-0003"/>
<rem:stability value = "SBV-0003"/>
<rem:triggeringEvent>
la empresa desea darse de alta en el sistema para publicar vacantes de empleo</rem:triggeringEvent>
<rem:precondition>
Ninguna</rem:precondition>
<rem:postcondition>
El usuario tendrá una cuenta en el sistema</rem:postcondition>
<rem:frequency>
<rem:value>
12
</rem:value>
<rem:timeUnit value = "TUV-0009"/>
</rem:frequency>
<rem:step oid = "STP-0019">
<rem:number>1</rem:number>
<rem:actorAction actor = "ACT-0002">
<rem:description>
selecciona la opcion registrarse</rem:description>
</rem:actorAction>
<rem:comments>
Ninguno</rem:comments>
</rem:step>
<rem:step oid = "STP-0020">
<rem:number>2</rem:number>
<rem:systemAction>
<rem:description>
muestra los campos que deben llenarse</rem:description>
</rem:systemAction>
<rem:comments>
Ninguno</rem:comments>
</rem:step>
<rem:step oid = "STP-0021">
<rem:number>3</rem:number>
<rem:actorAction actor = "ACT-0002">
<rem:description>
ingresa la información solicitada</rem:description>
</rem:actorAction>
<rem:stepException oid = "STX-0005">
<rem:condition>
falta algún campo por llenar</rem:condition>
<rem:systemAction>
<rem:description>
mostrará un mensaje de error &quot;llene todos los campos&quot;</rem:description>
</rem:systemAction>
<rem:termination value = "TEV-0002"/>
<rem:comments>
regresa al paso 3</rem:comments>
</rem:stepException>
<rem:comments>
Ninguno</rem:comments>
</rem:step>
<rem:step oid = "STP-0022">
<rem:number>4</rem:number>
<rem:systemAction>
<rem:description>
verifica que si ya se ha dado de alta esta empresa</rem:description>
</rem:systemAction>
<rem:stepException oid = "STX-0006">
<rem:condition>
la información ingresada ya existe en la base de datos</rem:condition>
<rem:systemAction>
<rem:description>
el sistema mostrará un mensaje de error &quot;Esta información ya existe&quot;</rem:description>
</rem:systemAction>
<rem:termination value = "TEV-0002"/>
<rem:comments>
regresa al paso 3</rem:comments>
</rem:stepException>
<rem:comments>
Ninguno</rem:comments>
</rem:step>
<rem:step oid = "STP-0023">
<rem:number>5</rem:number>
<rem:systemAction>
<rem:description>
dará de alta a esta empresa</rem:description>
</rem:systemAction>
<rem:comments>
Ninguno</rem:comments>
</rem:step>
<rem:step oid = "STP-0024">
<rem:number>6</rem:number>
<rem:systemAction>
<rem:description>
notificará a la empresa que se ha registrado correctamente</rem:description>
</rem:systemAction>
<rem:comments>
Ninguno</rem:comments>
</rem:step>
</rem:useCase>
<rem:useCase
 oid = "UC-0005">
<rem:name>
Modificar Persona Desempleada</rem:name>
<rem:version>
<rem:major>1</rem:major>
<rem:minor>0</rem:minor>
<rem:date>
<rem:year>2016</rem:year>
<rem:month>2</rem:month>
<rem:day>21</rem:day>
</rem:date>
</rem:version>
<rem:authors stakeholders ="STK-0001 "/>
<rem:comments>
Ninguno</rem:comments>
<rem:importance>
<rem:tbd/>
</rem:importance>
<rem:urgency>
<rem:tbd/>
</rem:urgency>
<rem:status>
<rem:tbd/>
</rem:status>
<rem:stability>
<rem:tbd/>
</rem:stability>
<rem:triggeringEvent>
el usuario desee actualizar su información académica, de contacto o profesional</rem:triggeringEvent>
<rem:precondition>
Haber ingresado al sistema</rem:precondition>
<rem:postcondition>
La información será actualizada</rem:postcondition>
<rem:frequency>
<rem:tbd/>
</rem:frequency>
<rem:step oid = "STP-0025">
<rem:number>1</rem:number>
<rem:actorAction actor = "ACT-0001">
<rem:description>
selecciona la opción actualizar información</rem:description>
</rem:actorAction>
<rem:comments>
Ninguno</rem:comments>
</rem:step>
<rem:step oid = "STP-0026">
<rem:number>2</rem:number>
<rem:systemAction>
<rem:description>
mostrará la información del usuario</rem:description>
</rem:systemAction>
<rem:comments>
Ninguno</rem:comments>
</rem:step>
<rem:step oid = "STP-0027">
<rem:number>3</rem:number>
<rem:actorAction actor = "ACT-0001">
<rem:description>
borra los datos que desea cambiar</rem:description>
</rem:actorAction>
<rem:comments>
Ninguno</rem:comments>
</rem:step>
<rem:step oid = "STP-0028">
<rem:number>4</rem:number>
<rem:actorAction actor = "ACT-0001">
<rem:description>
ingresa sus nuevos datos</rem:description>
</rem:actorAction>
<rem:comments>
Ninguno</rem:comments>
</rem:step>
<rem:step oid = "STP-0029">
<rem:number>5</rem:number>
<rem:systemAction>
<rem:description>
verifica que todos los campos estén llenos</rem:description>
</rem:systemAction>
<rem:stepException oid = "STX-0007">
<rem:condition>
algún campo quedó vacío</rem:condition>
<rem:systemAction>
<rem:description>
mostrará un mensaje &quot;falta uno o campos por llenar&quot;</rem:description>
</rem:systemAction>
<rem:termination value = "TEV-0002"/>
<rem:comments>
regresa al paso 4</rem:comments>
</rem:stepException>
<rem:comments>
Ninguno</rem:comments>
</rem:step>
<rem:step oid = "STP-0030">
<rem:number>6</rem:number>
<rem:systemAction>
<rem:description>
notificará al usuario que sus datos han sido actualizados correctamente</rem:description>
</rem:systemAction>
<rem:comments>
Ninguno</rem:comments>
</rem:step>
</rem:useCase>
<rem:useCase
 oid = "UC-0006">
<rem:name>
Modificar Empresa</rem:name>
<rem:version>
<rem:major>1</rem:major>
<rem:minor>0</rem:minor>
<rem:date>
<rem:year>2016</rem:year>
<rem:month>2</rem:month>
<rem:day>21</rem:day>
</rem:date>
</rem:version>
<rem:authors stakeholders ="STK-0001 "/>
<rem:comments>
Ninguno</rem:comments>
<rem:importance>
<rem:tbd/>
</rem:importance>
<rem:urgency>
<rem:tbd/>
</rem:urgency>
<rem:status>
<rem:tbd/>
</rem:status>
<rem:stability>
<rem:tbd/>
</rem:stability>
<rem:triggeringEvent>
el usuario desee actualizar su información de contacto </rem:triggeringEvent>
<rem:precondition>
Haber ingresado al sistema</rem:precondition>
<rem:postcondition>
La información será actualizada</rem:postcondition>
<rem:frequency>
<rem:tbd/>
</rem:frequency>
<rem:step oid = "STP-0031">
<rem:number>1</rem:number>
<rem:actorAction actor = "ACT-0002">
<rem:description>
selecciona la opción actualizar información</rem:description>
</rem:actorAction>
<rem:comments>
Ninguno</rem:comments>
</rem:step>
<rem:step oid = "STP-0032">
<rem:number>2</rem:number>
<rem:systemAction>
<rem:description>
mostrará la información de la empresa</rem:description>
</rem:systemAction>
<rem:comments>
Ninguno</rem:comments>
</rem:step>
<rem:step oid = "STP-0033">
<rem:number>3</rem:number>
<rem:actorAction actor = "ACT-0002">
<rem:description>
borra los datos que desea cambiar</rem:description>
</rem:actorAction>
<rem:comments>
Ninguno</rem:comments>
</rem:step>
<rem:step oid = "STP-0034">
<rem:number>4</rem:number>
<rem:actorAction actor = "ACT-0002">
<rem:description>
ingresa sus nuevos datos</rem:description>
</rem:actorAction>
<rem:comments>
Ninguno</rem:comments>
</rem:step>
<rem:step oid = "STP-0035">
<rem:number>5</rem:number>
<rem:systemAction>
<rem:description>
verifica que todos los campos estén llenos</rem:description>
</rem:systemAction>
<rem:stepException oid = "STX-0008">
<rem:condition>
algún campo quedó vacío</rem:condition>
<rem:systemAction>
<rem:description>
mostrará un mensaje &quot;falta uno o campos por llenar&quot;</rem:description>
</rem:systemAction>
<rem:termination value = "TEV-0002"/>
<rem:comments>
regresa al paso 4</rem:comments>
</rem:stepException>
<rem:comments>
Ninguno</rem:comments>
</rem:step>
<rem:step oid = "STP-0036">
<rem:number>6</rem:number>
<rem:systemAction>
<rem:description>
notificará a la empresa que sus datos han sido actualizados correctamente</rem:description>
</rem:systemAction>
<rem:comments>
Ninguno</rem:comments>
</rem:step>
</rem:useCase>
<rem:useCase
 oid = "UC-0007">
<rem:name>
Publicar Vacante</rem:name>
<rem:version>
<rem:major>1</rem:major>
<rem:minor>0</rem:minor>
<rem:date>
<rem:year>2016</rem:year>
<rem:month>2</rem:month>
<rem:day>21</rem:day>
</rem:date>
</rem:version>
<rem:authors stakeholders ="STK-0001 "/>
<rem:comments>
Ninguno</rem:comments>
<rem:importance value = "IMV-0002"/>
<rem:urgency value = "URV-0003"/>
<rem:status value = "STV-0003"/>
<rem:stability value = "SBV-0003"/>
<rem:triggeringEvent>
la empresa da a conocer una nueva vacante escribiendo el nombre del puesto, salario, horario de trabajo, los requisitos que se necesitan; esto para que la persona interesada en el puesto revisé si es apto para poder aplicar posteriormente para esta vacante.</rem:triggeringEvent>
<rem:precondition>
Haber ingresado al sistema con su cuenta</rem:precondition>
<rem:postcondition>
La empresa anunciará su puesto de trabajo que se encuentra desocupado</rem:postcondition>
<rem:frequency>
<rem:value>
10
</rem:value>
<rem:timeUnit value = "TUV-0008"/>
</rem:frequency>
<rem:step oid = "STP-0037">
<rem:number>1</rem:number>
<rem:actorAction actor = "ACT-0002">
<rem:description>
selecciona la opción empleo</rem:description>
</rem:actorAction>
<rem:comments>
Ninguno</rem:comments>
</rem:step>
<rem:step oid = "STP-0038">
<rem:number>2</rem:number>
<rem:actorAction actor = "ACT-0002">
<rem:description>
selecciona la opción anunciar vacante de empleo</rem:description>
</rem:actorAction>
<rem:comments>
Ninguno</rem:comments>
</rem:step>
<rem:step oid = "STP-0039">
<rem:number>3</rem:number>
<rem:systemAction>
<rem:description>
muestra los campos a llenar para anunciar su nueva oferta de trabajo</rem:description>
</rem:systemAction>
<rem:comments>
Ninguno</rem:comments>
</rem:step>
<rem:step oid = "STP-0042">
<rem:number>4</rem:number>
<rem:actorAction actor = "ACT-0002">
<rem:description>
escribe en los campos los requisitos para el puesto de trabajo y una descripción del mismo</rem:description>
</rem:actorAction>
<rem:comments>
Ninguno</rem:comments>
</rem:step>
<rem:step oid = "STP-0041">
<rem:number>5</rem:number>
<rem:systemAction>
<rem:description>
verifica que todos los campos hayan sido llenados</rem:description>
</rem:systemAction>
<rem:stepException oid = "STX-0009">
<rem:condition>
faltó algún campo por llenar</rem:condition>
<rem:systemAction>
<rem:description>
mostrará un mensaje de error &quot;llene todos los campos por favor&quot;</rem:description>
</rem:systemAction>
<rem:termination value = "TEV-0002"/>
<rem:comments>
regresa al paso 4</rem:comments>
</rem:stepException>
<rem:comments>
Ninguno</rem:comments>
</rem:step>
<rem:step oid = "STP-0043">
<rem:number>6</rem:number>
<rem:systemAction>
<rem:description>
notificará que la vacante fue publicada de manera correcta</rem:description>
</rem:systemAction>
<rem:comments>
Ninguno</rem:comments>
</rem:step>
</rem:useCase>
<rem:useCase
 oid = "UC-0008">
<rem:name>
Buscar</rem:name>
<rem:version>
<rem:major>1</rem:major>
<rem:minor>0</rem:minor>
<rem:date>
<rem:year>2016</rem:year>
<rem:month>2</rem:month>
<rem:day>22</rem:day>
</rem:date>
</rem:version>
<rem:authors stakeholders ="STK-0001 "/>
<rem:comments>
Ninguno</rem:comments>
<rem:importance value = "IMV-0003"/>
<rem:urgency value = "URV-0003"/>
<rem:status value = "STV-0003"/>
<rem:stability value = "SBV-0003"/>
<rem:triggeringEvent>
el usuario se encuentra en su perfil y desea hacer una búsqueda por empleo o empresa</rem:triggeringEvent>
<rem:precondition>
Haber iniciado sesión</rem:precondition>
<rem:postcondition>
La persona desempleada encontrará a la empresa que busca</rem:postcondition>
<rem:frequency>
<rem:value>
5
</rem:value>
<rem:timeUnit value = "TUV-0007"/>
</rem:frequency>
<rem:step oid = "STP-0044">
<rem:number>1</rem:number>
<rem:actorAction actor = "ACT-0001">
<rem:description>
escribe lo que desea encontrar en el buscador y da clic en buscar</rem:description>
</rem:actorAction>
<rem:comments>
Ninguno</rem:comments>
</rem:step>
<rem:step oid = "STP-0046">
<rem:number>2</rem:number>
<rem:systemAction>
<rem:description>
verifica que se haya escrito algo en el buscador</rem:description>
</rem:systemAction>
<rem:stepException oid = "STX-0010">
<rem:condition>
no se escribió nada en el buscador</rem:condition>
<rem:systemAction>
<rem:description>
mostará un mensaje de error &quot;Escriba algo que buscar&quot;</rem:description>
</rem:systemAction>
<rem:termination value = "TEV-0002"/>
<rem:comments>
regresa al paso 1</rem:comments>
</rem:stepException>
<rem:comments>
Ninguno</rem:comments>
</rem:step>
<rem:step oid = "STP-0047">
<rem:number>3</rem:number>
<rem:systemAction>
<rem:description>
mostrará los resultados de la búsqueda</rem:description>
</rem:systemAction>
<rem:comments>
Ninguno</rem:comments>
</rem:step>
</rem:useCase>
<rem:useCase
 oid = "UC-0009">
<rem:name>
Validar usuario persona desempleada</rem:name>
<rem:version>
<rem:major>1</rem:major>
<rem:minor>0</rem:minor>
<rem:date>
<rem:year>2016</rem:year>
<rem:month>2</rem:month>
<rem:day>26</rem:day>
</rem:date>
</rem:version>
<rem:authors stakeholders ="STK-0001 "/>
<rem:comments>
Ninguno</rem:comments>
<rem:importance>
<rem:tbd/>
</rem:importance>
<rem:urgency>
<rem:tbd/>
</rem:urgency>
<rem:status>
<rem:tbd/>
</rem:status>
<rem:stability>
<rem:tbd/>
</rem:stability>
<rem:triggeringEvent>
la persona desempleada deseen iniciar sesión</rem:triggeringEvent>
<rem:precondition>
Estar en la interfaz iniciar sesión</rem:precondition>
<rem:postcondition>
La persona desempleada ingresará al sistema</rem:postcondition>
<rem:frequency>
<rem:tbd/>
</rem:frequency>
<rem:step oid = "STP-0050">
<rem:number>1</rem:number>
<rem:actorAction actor = "ACT-0001">
<rem:description>
ingresa su nombre de usuario o correo electrónico</rem:description>
</rem:actorAction>
<rem:comments>
Ninguno</rem:comments>
</rem:step>
<rem:step oid = "STP-0051">
<rem:number>2</rem:number>
<rem:systemAction>
<rem:description>
consulta la información ingresada en la base de datos</rem:description>
</rem:systemAction>
<rem:stepException oid = "STX-0012">
<rem:condition>
la contraseña ingresada no corresponde con la de la base de datos</rem:condition>
<rem:systemAction>
<rem:description>
mostrará un mensaje de error</rem:description>
</rem:systemAction>
<rem:termination value = "TEV-0002"/>
<rem:comments>
regresa al paso1</rem:comments>
</rem:stepException>
<rem:comments>
Ninguno</rem:comments>
</rem:step>
<rem:step oid = "STP-0057">
<rem:number>3</rem:number>
<rem:useCaseAction useCase = "UC-0011"/><rem:comments>
Ninguno</rem:comments>
</rem:step>
</rem:useCase>
<rem:useCase
 oid = "UC-0010">
<rem:name>
Validar usuario empresa</rem:name>
<rem:version>
<rem:major>1</rem:major>
<rem:minor>0</rem:minor>
<rem:date>
<rem:year>2016</rem:year>
<rem:month>2</rem:month>
<rem:day>26</rem:day>
</rem:date>
</rem:version>
<rem:authors stakeholders ="STK-0001 "/>
<rem:comments>
Ninguno</rem:comments>
<rem:importance>
<rem:tbd/>
</rem:importance>
<rem:urgency>
<rem:tbd/>
</rem:urgency>
<rem:status>
<rem:tbd/>
</rem:status>
<rem:stability>
<rem:tbd/>
</rem:stability>
<rem:triggeringEvent>
la empresa deseen iniciar sesión</rem:triggeringEvent>
<rem:precondition>
Estar en la interfaz iniciar sesión</rem:precondition>
<rem:postcondition>
La empresa ingresará all sistema</rem:postcondition>
<rem:frequency>
<rem:tbd/>
</rem:frequency>
<rem:step oid = "STP-0053">
<rem:number>1</rem:number>
<rem:actorAction actor = "ACT-0002">
<rem:description>
ingresa su nombre de usuario o correo electrónico</rem:description>
</rem:actorAction>
<rem:comments>
Ninguno</rem:comments>
</rem:step>
<rem:step oid = "STP-0054">
<rem:number>2</rem:number>
<rem:systemAction>
<rem:description>
consulta la información ingresada en la base de datos</rem:description>
</rem:systemAction>
<rem:stepException oid = "STX-0013">
<rem:condition>
la información no corresponde con la de la base de datos</rem:condition>
<rem:systemAction>
<rem:description>
mostrará un mensaje de error</rem:description>
</rem:systemAction>
<rem:termination value = "TEV-0002"/>
<rem:comments>
regresa al paso1</rem:comments>
</rem:stepException>
<rem:comments>
Ninguno</rem:comments>
</rem:step>
<rem:step oid = "STP-0058">
<rem:number>3</rem:number>
<rem:useCaseAction useCase = "UC-0012"/><rem:comments>
Ninguno</rem:comments>
</rem:step>
</rem:useCase>
<rem:useCase
 oid = "UC-0011">
<rem:name>
Validar contraseña persona desempleada</rem:name>
<rem:version>
<rem:major>1</rem:major>
<rem:minor>0</rem:minor>
<rem:date>
<rem:year>2016</rem:year>
<rem:month>2</rem:month>
<rem:day>26</rem:day>
</rem:date>
</rem:version>
<rem:authors stakeholders ="STK-0001 "/>
<rem:comments>
Ninguno</rem:comments>
<rem:importance>
<rem:tbd/>
</rem:importance>
<rem:urgency>
<rem:tbd/>
</rem:urgency>
<rem:status>
<rem:tbd/>
</rem:status>
<rem:stability>
<rem:tbd/>
</rem:stability>
<rem:triggeringEvent>
la persona desempleada desee iniciar sesión</rem:triggeringEvent>
<rem:precondition>
Estar en la interfaz iniciar sesión</rem:precondition>
<rem:postcondition>
La persona desempleada ingresará al sistema</rem:postcondition>
<rem:frequency>
<rem:tbd/>
</rem:frequency>
<rem:step oid = "STP-0055">
<rem:number>1</rem:number>
<rem:actorAction actor = "ACT-0001">
<rem:description>
escribe su contraseña</rem:description>
</rem:actorAction>
<rem:comments>
Ninguno</rem:comments>
</rem:step>
<rem:step oid = "STP-0056">
<rem:number>2</rem:number>
<rem:systemAction>
<rem:description>
consulta la información en la base de datos </rem:description>
</rem:systemAction>
<rem:stepException oid = "STX-0014">
<rem:condition>
la contraseña ingresada no corresponde con la que existe en la base de datos</rem:condition>
<rem:systemAction>
<rem:description>
mostrará un mensaje de error</rem:description>
</rem:systemAction>
<rem:termination value = "TEV-0002"/>
<rem:comments>
regresa al paso 1</rem:comments>
</rem:stepException>
<rem:comments>
Ninguno</rem:comments>
</rem:step>
<rem:step oid = "STP-0060">
<rem:number>3</rem:number>
<rem:useCaseAction useCase = "UC-0013"/><rem:comments>
Ninguno</rem:comments>
</rem:step>
</rem:useCase>
<rem:useCase
 oid = "UC-0012">
<rem:name>
Validar contraseña empresa</rem:name>
<rem:version>
<rem:major>1</rem:major>
<rem:minor>0</rem:minor>
<rem:date>
<rem:year>2016</rem:year>
<rem:month>2</rem:month>
<rem:day>26</rem:day>
</rem:date>
</rem:version>
<rem:authors stakeholders ="STK-0001 "/>
<rem:comments>
Ninguno</rem:comments>
<rem:importance>
<rem:tbd/>
</rem:importance>
<rem:urgency>
<rem:tbd/>
</rem:urgency>
<rem:status>
<rem:tbd/>
</rem:status>
<rem:stability>
<rem:tbd/>
</rem:stability>
<rem:triggeringEvent>
</rem:triggeringEvent>
<rem:precondition>
<rem:tbd/></rem:precondition>
<rem:postcondition>
<rem:tbd/></rem:postcondition>
<rem:frequency>
<rem:tbd/>
</rem:frequency>
<rem:step oid = "STP-0061">
<rem:number>1</rem:number>
<rem:actorAction actor = "ACT-0002">
<rem:description>
ingresa su contraseña</rem:description>
</rem:actorAction>
<rem:comments>
Ninguno</rem:comments>
</rem:step>
<rem:step oid = "STP-0062">
<rem:number>2</rem:number>
<rem:systemAction>
<rem:description>
consulta la información ingresada en la base de datos</rem:description>
</rem:systemAction>
<rem:stepException oid = "STX-0015">
<rem:condition>
la contraseña ingresada no existe en la base de datos</rem:condition>
<rem:systemAction>
<rem:description>
mostrará un mensaje de error</rem:description>
</rem:systemAction>
<rem:termination value = "TEV-0002"/>
<rem:comments>
regresa al paso 1</rem:comments>
</rem:stepException>
<rem:stepException oid = "STX-0016">
<rem:condition>
la contraseña ingresada no coincide con el usuario</rem:condition>
<rem:systemAction>
<rem:description>
mostrará un mensaje de error</rem:description>
</rem:systemAction>
<rem:termination value = "TEV-0002"/>
<rem:comments>
regresa al paso 1</rem:comments>
</rem:stepException>
<rem:comments>
Ninguno</rem:comments>
</rem:step>
<rem:step oid = "STP-0063">
<rem:number>3</rem:number>
<rem:useCaseAction useCase = "UC-0013"/><rem:comments>
Ninguno</rem:comments>
</rem:step>
</rem:useCase>
<rem:useCase
 oid = "UC-0013">
<rem:name>
Verificar tipo_usuario</rem:name>
<rem:version>
<rem:major>1</rem:major>
<rem:minor>0</rem:minor>
<rem:date>
<rem:year>2016</rem:year>
<rem:month>2</rem:month>
<rem:day>28</rem:day>
</rem:date>
</rem:version>
<rem:authors stakeholders ="STK-0001 "/>
<rem:comments>
Ninguno</rem:comments>
<rem:importance>
<rem:tbd/>
</rem:importance>
<rem:urgency>
<rem:tbd/>
</rem:urgency>
<rem:status>
<rem:tbd/>
</rem:status>
<rem:stability>
<rem:tbd/>
</rem:stability>
<rem:triggeringEvent>
el usuario y la contraseña han sido validados para iniciar sesión</rem:triggeringEvent>
<rem:precondition>
Haber validado usuario y contraseña</rem:precondition>
<rem:postcondition>
Se identificará el tipo de usuario para presentar la pantalla de inicio correspondiente</rem:postcondition>
<rem:frequency>
<rem:tbd/>
</rem:frequency>
<rem:step oid = "STP-0065">
<rem:number>1</rem:number>
<rem:systemAction>
<rem:description>
consulta en la base de datos el usuario ingresado</rem:description>
</rem:systemAction>
<rem:comments>
Ninguno</rem:comments>
</rem:step>
<rem:step oid = "STP-0068">
<rem:number>2</rem:number>
<rem:systemAction>
<rem:description>
consulta la tabla de usuarios</rem:description>
</rem:systemAction>
<rem:stepException oid = "STX-0021">
<rem:condition>
el usuario es de tipo 1</rem:condition>
<rem:systemAction>
<rem:description>
el sistema deduce que el usuario es una empresa</rem:description>
</rem:systemAction>
<rem:termination value = "TEV-0003"/>
<rem:comments>
Ninguno</rem:comments>
</rem:stepException>
<rem:stepException oid = "STX-0022">
<rem:condition>
el usuario es de tipo 2</rem:condition>
<rem:systemAction>
<rem:description>
deduce que el usuario es una persona desempleada</rem:description>
</rem:systemAction>
<rem:termination value = "TEV-0003"/>
<rem:comments>
Ninguno</rem:comments>
</rem:stepException>
<rem:comments>
Ninguno</rem:comments>
</rem:step>
</rem:useCase>
<rem:useCase
 oid = "UC-0014">
<rem:name>
Mostrar interfaz</rem:name>
<rem:version>
<rem:major>1</rem:major>
<rem:minor>0</rem:minor>
<rem:date>
<rem:year>2016</rem:year>
<rem:month>2</rem:month>
<rem:day>28</rem:day>
</rem:date>
</rem:version>
<rem:authors stakeholders ="STK-0001 "/>
<rem:comments>
Ninguno</rem:comments>
<rem:importance>
<rem:tbd/>
</rem:importance>
<rem:urgency>
<rem:tbd/>
</rem:urgency>
<rem:status>
<rem:tbd/>
</rem:status>
<rem:stability>
<rem:tbd/>
</rem:stability>
<rem:triggeringEvent>
el sistema ha deducid el tipo de usuario</rem:triggeringEvent>
<rem:precondition>
Conocer el tipo de usuario</rem:precondition>
<rem:postcondition>
Presentar la pantalla de inicio correspondiente de acuerdo al nivel de acceso(tipo de usuario)</rem:postcondition>
<rem:frequency>
<rem:tbd/>
</rem:frequency>
<rem:step oid = "STP-0069">
<rem:number>1</rem:number>
<rem:condition>
el tipo de usuario es numero 1</rem:condition>
<rem:systemAction>
<rem:description>
mostrará la interfaz de inicio para empresas</rem:description>
</rem:systemAction>
<rem:comments>
Ninguno</rem:comments>
</rem:step>
<rem:step oid = "STP-0071">
<rem:number>2</rem:number>
<rem:condition>
no es un tipo de usuario 1, entonces es tipo de usuario 2</rem:condition>
<rem:systemAction>
<rem:description>
mostrará la pantalla de inicio para persona desempleada</rem:description>
</rem:systemAction>
<rem:comments>
Ninguno</rem:comments>
</rem:step>
</rem:useCase>
<rem:useCase
 oid = "UC-0015">
<rem:name>
Generar usuario persona desempleada</rem:name>
<rem:version>
<rem:major>1</rem:major>
<rem:minor>0</rem:minor>
<rem:date>
<rem:year>2016</rem:year>
<rem:month>2</rem:month>
<rem:day>28</rem:day>
</rem:date>
</rem:version>
<rem:authors stakeholders ="STK-0001 "/>
<rem:comments>
Ninguno</rem:comments>
<rem:importance>
<rem:tbd/>
</rem:importance>
<rem:urgency>
<rem:tbd/>
</rem:urgency>
<rem:status>
<rem:tbd/>
</rem:status>
<rem:stability>
<rem:tbd/>
</rem:stability>
<rem:triggeringEvent>
la persona desempleada desea darse de alta en el sistema</rem:triggeringEvent>
<rem:precondition>
Ninguna</rem:precondition>
<rem:postcondition>
El sistema generará un usuario a la persona desempleada</rem:postcondition>
<rem:frequency>
<rem:tbd/>
</rem:frequency>
<rem:step oid = "STP-0080">
<rem:number>1</rem:number>
<rem:actorAction actor = "ACT-0001">
<rem:description>
Ingresará su nombre completo</rem:description>
</rem:actorAction>
<rem:comments>
Ninguno</rem:comments>
</rem:step>
<rem:step oid = "STP-0072">
<rem:number>2</rem:number>
<rem:systemAction>
<rem:description>
tomará las primeras 3 letras de su nombre</rem:description>
</rem:systemAction>
<rem:comments>
Ninguno</rem:comments>
</rem:step>
<rem:step oid = "STP-0073">
<rem:number>3</rem:number>
<rem:systemAction>
<rem:description>
tomará las primeras 3 letras de su apellido materno</rem:description>
</rem:systemAction>
<rem:comments>
Ninguno</rem:comments>
</rem:step>
<rem:step oid = "STP-0074">
<rem:number>4</rem:number>
<rem:systemAction>
<rem:description>
tomará las 3 primeras letras de su apellido paterno</rem:description>
</rem:systemAction>
<rem:comments>
Ninguno</rem:comments>
</rem:step>
<rem:step oid = "STP-0075">
<rem:number>5</rem:number>
<rem:systemAction>
<rem:description>
concatenará las 6 letras que obtuvo de su nombre completo</rem:description>
</rem:systemAction>
<rem:comments>
Ninguno</rem:comments>
</rem:step>
</rem:useCase>
<rem:useCase
 oid = "UC-0016">
<rem:name>
Validar correo</rem:name>
<rem:version>
<rem:major>1</rem:major>
<rem:minor>0</rem:minor>
<rem:date>
<rem:year>2016</rem:year>
<rem:month>2</rem:month>
<rem:day>28</rem:day>
</rem:date>
</rem:version>
<rem:authors stakeholders ="STK-0001 "/>
<rem:comments>
Ninguno</rem:comments>
<rem:importance>
<rem:tbd/>
</rem:importance>
<rem:urgency>
<rem:tbd/>
</rem:urgency>
<rem:status>
<rem:tbd/>
</rem:status>
<rem:stability>
<rem:tbd/>
</rem:stability>
<rem:triggeringEvent>
cuando la persona desempleada desee darse de alta en el sistema</rem:triggeringEvent>
<rem:precondition>
Ninguna</rem:precondition>
<rem:postcondition>
El sistema verificará que el correo sea válido</rem:postcondition>
<rem:frequency>
<rem:tbd/>
</rem:frequency>
<rem:step oid = "STP-0079">
<rem:number>1</rem:number>
<rem:actorAction actor = "ACT-0001">
<rem:description>
escribe su dirección de correo electrónico</rem:description>
</rem:actorAction>
<rem:comments>
Ninguno</rem:comments>
</rem:step>
<rem:step oid = "STP-0076">
<rem:number>2</rem:number>
<rem:systemAction>
<rem:description>
verifica que el correo contenga números y letras</rem:description>
</rem:systemAction>
<rem:comments>
Ninguno</rem:comments>
</rem:step>
<rem:step oid = "STP-0077">
<rem:number>3</rem:number>
<rem:systemAction>
<rem:description>
verifica que el correo escrito contenga un arroba</rem:description>
</rem:systemAction>
<rem:comments>
Ninguno</rem:comments>
</rem:step>
<rem:step oid = "STP-0078">
<rem:number>4</rem:number>
<rem:systemAction>
<rem:description>
verifica el dominio del correo electrónico ingresado</rem:description>
</rem:systemAction>
<rem:stepException oid = "STX-0026">
<rem:condition>
la dirección de correo electrónico no corresponde con una válida</rem:condition>
<rem:systemAction>
<rem:description>
mostrará un mensaje de error</rem:description>
</rem:systemAction>
<rem:termination value = "TEV-0002"/>
<rem:comments>
regresa al paso 1</rem:comments>
</rem:stepException>
<rem:comments>
Ninguno</rem:comments>
</rem:step>
</rem:useCase>
<rem:useCase
 oid = "UC-0017">
<rem:name>
Validar fecha nacimiento</rem:name>
<rem:version>
<rem:major>1</rem:major>
<rem:minor>0</rem:minor>
<rem:date>
<rem:year>2016</rem:year>
<rem:month>2</rem:month>
<rem:day>28</rem:day>
</rem:date>
</rem:version>
<rem:authors stakeholders ="STK-0001 "/>
<rem:comments>
Ninguno</rem:comments>
<rem:importance>
<rem:tbd/>
</rem:importance>
<rem:urgency>
<rem:tbd/>
</rem:urgency>
<rem:status>
<rem:tbd/>
</rem:status>
<rem:stability>
<rem:tbd/>
</rem:stability>
<rem:triggeringEvent>
la persona desempleada desee darse de alta en el sistema</rem:triggeringEvent>
<rem:precondition>
Ninguna</rem:precondition>
<rem:postcondition>
El sistema verificará que la fecha ingresada sea correcta</rem:postcondition>
<rem:frequency>
<rem:tbd/>
</rem:frequency>
<rem:step oid = "STP-0081">
<rem:number>1</rem:number>
<rem:actorAction actor = "ACT-0001">
<rem:description>
ingresará su fecha de nacimiento</rem:description>
</rem:actorAction>
<rem:comments>
Ninguno</rem:comments>
</rem:step>
<rem:step oid = "STP-0082">
<rem:number>2</rem:number>
<rem:systemAction>
<rem:description>
verificará que el año ingresado sea diferente del actual</rem:description>
</rem:systemAction>
<rem:stepException oid = "STX-0027">
<rem:condition>
el año ingresado es el actual</rem:condition>
<rem:systemAction>
<rem:description>
mostrará un mensaje de error</rem:description>
</rem:systemAction>
<rem:termination value = "TEV-0002"/>
<rem:comments>
regresa al paso1</rem:comments>
</rem:stepException>
<rem:comments>
Ninguno</rem:comments>
</rem:step>
<rem:step oid = "STP-0083">
<rem:number>3</rem:number>
<rem:systemAction>
<rem:description>
verificará que el año ingresado sea de una persona mayor o igual a 18 años</rem:description>
</rem:systemAction>
<rem:stepException oid = "STX-0028">
<rem:condition>
la persona es menor de 18 años</rem:condition>
<rem:systemAction>
<rem:description>
mostrará un mensaje de error</rem:description>
</rem:systemAction>
<rem:termination value = "TEV-0003"/>
<rem:comments>
Ninguno</rem:comments>
</rem:stepException>
<rem:comments>
Ninguno</rem:comments>
</rem:step>
</rem:useCase>
<rem:useCase
 oid = "UC-0018">
<rem:name>
Validar nombre existente</rem:name>
<rem:version>
<rem:major>1</rem:major>
<rem:minor>0</rem:minor>
<rem:date>
<rem:year>2016</rem:year>
<rem:month>2</rem:month>
<rem:day>28</rem:day>
</rem:date>
</rem:version>
<rem:authors stakeholders ="STK-0001 "/>
<rem:comments>
Ninguno</rem:comments>
<rem:importance>
<rem:tbd/>
</rem:importance>
<rem:urgency>
<rem:tbd/>
</rem:urgency>
<rem:status>
<rem:tbd/>
</rem:status>
<rem:stability>
<rem:tbd/>
</rem:stability>
<rem:triggeringEvent>
cuando la persona desempleada desee darse de alta en el sistema</rem:triggeringEvent>
<rem:precondition>
Ninguna</rem:precondition>
<rem:postcondition>
El sistema validará si la persona desempleada que desea registrarse ya existe en la base de datos</rem:postcondition>
<rem:frequency>
<rem:tbd/>
</rem:frequency>
<rem:step oid = "STP-0084">
<rem:number>1</rem:number>
<rem:actorAction actor = "ACT-0001">
<rem:description>
ingresa su nombre completo</rem:description>
</rem:actorAction>
<rem:comments>
Ninguno</rem:comments>
</rem:step>
<rem:step oid = "STP-0085">
<rem:number>2</rem:number>
<rem:systemAction>
<rem:description>
envía el nombre completo a la base de datos</rem:description>
</rem:systemAction>
<rem:comments>
Ninguno</rem:comments>
</rem:step>
<rem:step oid = "STP-0086">
<rem:number>3</rem:number>
<rem:systemAction>
<rem:description>
consulta la información en la tabla persona desempleada</rem:description>
</rem:systemAction>
<rem:stepException oid = "STX-0029">
<rem:condition>
el nombre ya existe en la base de datos</rem:condition>
<rem:systemAction>
<rem:description>
mostrará un mensaje de error</rem:description>
</rem:systemAction>
<rem:termination value = "TEV-0003"/>
<rem:comments>
Ninguno</rem:comments>
</rem:stepException>
<rem:comments>
Ninguno</rem:comments>
</rem:step>
</rem:useCase>
<rem:useCase
 oid = "UC-0019">
<rem:name>
Generar captcha</rem:name>
<rem:version>
<rem:major>1</rem:major>
<rem:minor>0</rem:minor>
<rem:date>
<rem:year>2016</rem:year>
<rem:month>2</rem:month>
<rem:day>28</rem:day>
</rem:date>
</rem:version>
<rem:comments>
Ninguno</rem:comments>
<rem:importance>
<rem:tbd/>
</rem:importance>
<rem:urgency>
<rem:tbd/>
</rem:urgency>
<rem:status>
<rem:tbd/>
</rem:status>
<rem:stability>
<rem:tbd/>
</rem:stability>
<rem:triggeringEvent>
cuando una persona desempleada o empresa desee darse de alta en el sistema</rem:triggeringEvent>
<rem:precondition>
Ninguna</rem:precondition>
<rem:postcondition>
El usuario visualizará el captcha</rem:postcondition>
<rem:frequency>
<rem:tbd/>
</rem:frequency>
<rem:step oid = "STP-0087">
<rem:number>1</rem:number>
<rem:systemAction>
<rem:description>
generará un código alfanumérico</rem:description>
</rem:systemAction>
<rem:comments>
Ninguno</rem:comments>
</rem:step>
<rem:step oid = "STP-0088">
<rem:number>2</rem:number>
<rem:systemAction>
<rem:description>
guardará el código a una variable de sesión</rem:description>
</rem:systemAction>
<rem:comments>
Ninguno</rem:comments>
</rem:step>
<rem:step oid = "STP-0089">
<rem:number>3</rem:number>
<rem:systemAction>
<rem:description>
mostrará la imagen que contiene el captcha</rem:description>
</rem:systemAction>
<rem:comments>
Ninguno</rem:comments>
</rem:step>
</rem:useCase>
<rem:useCase
 oid = "UC-0020">
<rem:name>
Validar captcha</rem:name>
<rem:version>
<rem:major>1</rem:major>
<rem:minor>0</rem:minor>
<rem:date>
<rem:year>2016</rem:year>
<rem:month>2</rem:month>
<rem:day>28</rem:day>
</rem:date>
</rem:version>
<rem:authors stakeholders ="STK-0001 "/>
<rem:comments>
Ninguno</rem:comments>
<rem:importance>
<rem:tbd/>
</rem:importance>
<rem:urgency>
<rem:tbd/>
</rem:urgency>
<rem:status>
<rem:tbd/>
</rem:status>
<rem:stability>
<rem:tbd/>
</rem:stability>
<rem:triggeringEvent>
cuando el usuario desee enviar su información para registrarse en el sistema</rem:triggeringEvent>
<rem:precondition>
Ninguna</rem:precondition>
<rem:postcondition>
El captcha será validado</rem:postcondition>
<rem:frequency>
<rem:tbd/>
</rem:frequency>
<rem:step oid = "STP-0092">
<rem:number>1</rem:number>
<rem:systemAction>
<rem:description>
guardará temporalmente el captcha ingresado por el usuario en una variable de sesión</rem:description>
</rem:systemAction>
<rem:comments>
Ninguno</rem:comments>
</rem:step>
<rem:step oid = "STP-0093">
<rem:number>2</rem:number>
<rem:systemAction>
<rem:description>
consultará el captcha almacenada en la variable de sesión</rem:description>
</rem:systemAction>
<rem:stepException oid = "STX-0030">
<rem:condition>
el captcha que ingresó el usuario no corresponde con el generado</rem:condition>
<rem:useCaseAction useCase = "UC-0019"/><rem:termination value = "TEV-0002"/>
<rem:comments>
regresa al paso 1</rem:comments>
</rem:stepException>
<rem:comments>
Ninguno</rem:comments>
</rem:step>
</rem:useCase>
<rem:useCase
 oid = "UC-0021">
<rem:name>
Verificar cuenta persona desempleada</rem:name>
<rem:version>
<rem:major>1</rem:major>
<rem:minor>0</rem:minor>
<rem:date>
<rem:year>2016</rem:year>
<rem:month>2</rem:month>
<rem:day>28</rem:day>
</rem:date>
</rem:version>
<rem:authors stakeholders ="STK-0001 "/>
<rem:comments>
Ninguno</rem:comments>
<rem:importance>
<rem:tbd/>
</rem:importance>
<rem:urgency>
<rem:tbd/>
</rem:urgency>
<rem:status>
<rem:tbd/>
</rem:status>
<rem:stability>
<rem:tbd/>
</rem:stability>
<rem:triggeringEvent>
cuando algún usuario se haya dado de alta en el sistema</rem:triggeringEvent>
<rem:precondition>
Haberse registrado en el sistema</rem:precondition>
<rem:postcondition>
El usuario podrá acceder a su nueva cuenta</rem:postcondition>
<rem:frequency>
<rem:tbd/>
</rem:frequency>
<rem:step oid = "STP-0094">
<rem:number>1</rem:number>
<rem:systemAction>
<rem:description>
enviará un link a la dirección de correo electrónico que el usuario proporcionó</rem:description>
</rem:systemAction>
<rem:comments>
Ninguno</rem:comments>
</rem:step>
<rem:step oid = "STP-0095">
<rem:number>2</rem:number>
<rem:actorAction actor = "ACT-0001">
<rem:description>
ingresará a su correo y dará clic al enlace que le ha sido enviado</rem:description>
</rem:actorAction>
<rem:stepException oid = "STX-0031">
<rem:condition>
el actor persona desempleada no ingresó a su correo electrónico para verificar la cuenta mediante el enlance proporcionado</rem:condition>
<rem:systemAction>
<rem:description>
no permitirá que inicie sesión</rem:description>
</rem:systemAction>
<rem:termination value = "TEV-0003"/>
<rem:comments>
Ninguno</rem:comments>
</rem:stepException>
<rem:comments>
Ninguno</rem:comments>
</rem:step>
<rem:step oid = "STP-0098">
<rem:number>3</rem:number>
<rem:systemAction>
<rem:description>
redirigirá al usuario a otra página</rem:description>
</rem:systemAction>
<rem:comments>
Ninguno</rem:comments>
</rem:step>
<rem:step oid = "STP-0097">
<rem:number>4</rem:number>
<rem:actorAction actor = "ACT-0001">
<rem:description>
ingresará sus datos de inicio de sesión</rem:description>
</rem:actorAction>
<rem:comments>
Ninguno</rem:comments>
</rem:step>
<rem:step oid = "STP-0096">
<rem:number>5</rem:number>
<rem:systemAction>
<rem:description>
cambiará actualizará el status de la cuenta a 1</rem:description>
</rem:systemAction>
<rem:comments>
0=desactivada<br/>1=activada</rem:comments>
</rem:step>
</rem:useCase>
<rem:useCase
 oid = "UC-0022">
<rem:name>
Verificar cuenta empresa</rem:name>
<rem:version>
<rem:major>1</rem:major>
<rem:minor>0</rem:minor>
<rem:date>
<rem:year>2016</rem:year>
<rem:month>2</rem:month>
<rem:day>28</rem:day>
</rem:date>
</rem:version>
<rem:authors stakeholders ="STK-0001 "/>
<rem:comments>
Ninguno</rem:comments>
<rem:importance value = "IMV-0003"/>
<rem:urgency value = "URV-0003"/>
<rem:status value = "STV-0003"/>
<rem:stability value = "SBV-0003"/>
<rem:triggeringEvent>
cuando algún usuario se haya dado de alta en el sistema</rem:triggeringEvent>
<rem:precondition>
Haberse registrado en el sistema</rem:precondition>
<rem:postcondition>
El usuario podrá acceder a su nueva cuenta</rem:postcondition>
<rem:frequency>
<rem:value>
12
</rem:value>
<rem:timeUnit value = "TUV-0008"/>
</rem:frequency>
<rem:step oid = "STP-0099">
<rem:number>1</rem:number>
<rem:systemAction>
<rem:description>
enviará un link a la dirección de correo electrónico que el usuario proporcionó</rem:description>
</rem:systemAction>
<rem:comments>
Ninguno</rem:comments>
</rem:step>
<rem:step oid = "STP-0100">
<rem:number>2</rem:number>
<rem:actorAction actor = "ACT-0002">
<rem:description>
ingresará a su correo y dará clic al enlace que le ha sido enviado</rem:description>
</rem:actorAction>
<rem:stepException oid = "STX-0032">
<rem:condition>
el actor persona desempleada no ingresó a su correo electrónico para verificar la cuenta mediante el enlance proporcionado</rem:condition>
<rem:systemAction>
<rem:description>
no permitirá que inicie sesión</rem:description>
</rem:systemAction>
<rem:termination value = "TEV-0003"/>
<rem:comments>
Ninguno</rem:comments>
</rem:stepException>
<rem:comments>
Ninguno</rem:comments>
</rem:step>
<rem:step oid = "STP-0101">
<rem:number>3</rem:number>
<rem:systemAction>
<rem:description>
redirigirá al usuario a otra página</rem:description>
</rem:systemAction>
<rem:comments>
Ninguno</rem:comments>
</rem:step>
<rem:step oid = "STP-0102">
<rem:number>4</rem:number>
<rem:actorAction actor = "ACT-0002">
<rem:description>
ingresará sus datos de inicio de sesión</rem:description>
</rem:actorAction>
<rem:comments>
Ninguno</rem:comments>
</rem:step>
<rem:step oid = "STP-0103">
<rem:number>5</rem:number>
<rem:systemAction>
<rem:description>
cambiará actualizará el status de la cuenta a 1</rem:description>
</rem:systemAction>
<rem:comments>
0=desactivada<br/>1=activada</rem:comments>
</rem:step>
</rem:useCase>
<rem:useCase
 oid = "UC-0023">
<rem:name>
Validar empresa</rem:name>
<rem:version>
<rem:major>1</rem:major>
<rem:minor>0</rem:minor>
<rem:date>
<rem:year>2016</rem:year>
<rem:month>2</rem:month>
<rem:day>28</rem:day>
</rem:date>
</rem:version>
<rem:authors stakeholders ="STK-0001 "/>
<rem:comments>
Ninguno</rem:comments>
<rem:importance value = "IMV-0003"/>
<rem:urgency value = "URV-0003"/>
<rem:status value = "STV-0003"/>
<rem:stability value = "SBV-0003"/>
<rem:triggeringEvent>
la empresa desee darse de alta en el sistema</rem:triggeringEvent>
<rem:precondition>
Ninguna</rem:precondition>
<rem:postcondition>
Se verificará la autenticidad de la empresa</rem:postcondition>
<rem:frequency>
<rem:value>
10
</rem:value>
<rem:timeUnit value = "TUV-0009"/>
</rem:frequency>
<rem:step oid = "STP-0104">
<rem:number>1</rem:number>
<rem:actorAction actor = "ACT-0002">
<rem:description>
ingresa su nombre de la compañía</rem:description>
</rem:actorAction>
<rem:comments>
Ninguno</rem:comments>
</rem:step>
<rem:step oid = "STP-0105">
<rem:number>2</rem:number>
<rem:systemAction>
<rem:description>
verificará si la empresa esta dada de alta como tal</rem:description>
</rem:systemAction>
<rem:stepException oid = "STX-0033">
<rem:condition>
la empresa ingresada no existe</rem:condition>
<rem:systemAction>
<rem:description>
mostrará un mensaje de error</rem:description>
</rem:systemAction>
<rem:termination value = "TEV-0003"/>
<rem:comments>
Ninguno</rem:comments>
</rem:stepException>
<rem:comments>
Ninguno</rem:comments>
</rem:step>
<rem:step oid = "STP-0106">
<rem:number>3</rem:number>
<rem:systemAction>
<rem:description>
mostrará un mensaje que la autencidad de la empresa registrada ha sido verificada con éxito</rem:description>
</rem:systemAction>
<rem:comments>
Ninguno</rem:comments>
</rem:step>
</rem:useCase>
<rem:useCase
 oid = "UC-0024">
<rem:name>
Validar empresa existente</rem:name>
<rem:version>
<rem:major>1</rem:major>
<rem:minor>0</rem:minor>
<rem:date>
<rem:year>2016</rem:year>
<rem:month>2</rem:month>
<rem:day>28</rem:day>
</rem:date>
</rem:version>
<rem:authors stakeholders ="STK-0001 "/>
<rem:comments>
Ninguno</rem:comments>
<rem:importance>
<rem:tbd/>
</rem:importance>
<rem:urgency>
<rem:tbd/>
</rem:urgency>
<rem:status>
<rem:tbd/>
</rem:status>
<rem:stability>
<rem:tbd/>
</rem:stability>
<rem:triggeringEvent>
cuando una empresa desee darse de alta en el sistema</rem:triggeringEvent>
<rem:precondition>
Ninguna</rem:precondition>
<rem:postcondition>
El sistema validará si la empresa que desea registrarse ya existe en la base de datos</rem:postcondition>
<rem:frequency>
<rem:value>
10
</rem:value>
<rem:timeUnit value = "TUV-0009"/>
</rem:frequency>
<rem:step oid = "STP-0107">
<rem:number>1</rem:number>
<rem:actorAction actor = "ACT-0002">
<rem:description>
ingresa el nombre de la compañía, su dirección y rfc</rem:description>
</rem:actorAction>
<rem:comments>
Ninguno</rem:comments>
</rem:step>
<rem:step oid = "STP-0108">
<rem:number>2</rem:number>
<rem:systemAction>
<rem:description>
envía la información ingresada a la base de datos</rem:description>
</rem:systemAction>
<rem:comments>
Ninguno</rem:comments>
</rem:step>
<rem:step oid = "STP-0109">
<rem:number>3</rem:number>
<rem:systemAction>
<rem:description>
consulta la información en la tabla empresa</rem:description>
</rem:systemAction>
<rem:stepException oid = "STX-0034">
<rem:condition>
la empresa ya existe en la base de datos</rem:condition>
<rem:systemAction>
<rem:description>
mostrará un mensaje de error</rem:description>
</rem:systemAction>
<rem:termination value = "TEV-0003"/>
<rem:comments>
Ninguno</rem:comments>
</rem:stepException>
<rem:comments>
Ninguno</rem:comments>
</rem:step>
</rem:useCase>
<rem:useCase
 oid = "UC-0025">
<rem:name>
Validar campos vacíos persona desempleada</rem:name>
<rem:version>
<rem:major>1</rem:major>
<rem:minor>0</rem:minor>
<rem:date>
<rem:year>2016</rem:year>
<rem:month>2</rem:month>
<rem:day>28</rem:day>
</rem:date>
</rem:version>
<rem:authors stakeholders ="STK-0001 "/>
<rem:comments>
Datos de contacto, estudios, experiencia, contraseña o usuario.</rem:comments>
<rem:importance value = "IMV-0003"/>
<rem:urgency value = "URV-0003"/>
<rem:status value = "STV-0003"/>
<rem:stability value = "SBV-0003"/>
<rem:triggeringEvent>
cuando la persona desempleada desee actualizar alguno de sus datos</rem:triggeringEvent>
<rem:precondition>
Estar registrado en el sistema.<br/>Haber iniciado sesión.</rem:precondition>
<rem:postcondition>
La persona desempleada actualizará sus datos</rem:postcondition>
<rem:frequency>
<rem:value>
10
</rem:value>
<rem:timeUnit value = "TUV-0008"/>
</rem:frequency>
<rem:step oid = "STP-0111">
<rem:number>1</rem:number>
<rem:useCaseAction useCase = "UC-0005"/><rem:stepException oid = "STX-0035">
<rem:condition>
algún campo esta vacío</rem:condition>
<rem:systemAction>
<rem:description>
mostrará un mensaje de error</rem:description>
</rem:systemAction>
<rem:termination value = "TEV-0002"/>
<rem:comments>
regresa al paso 1</rem:comments>
</rem:stepException>
<rem:comments>
Ninguno</rem:comments>
</rem:step>
</rem:useCase>
<rem:useCase
 oid = "UC-0026">
<rem:name>
Validar campos vacíos empresa</rem:name>
<rem:version>
<rem:major>1</rem:major>
<rem:minor>0</rem:minor>
<rem:date>
<rem:year>2016</rem:year>
<rem:month>2</rem:month>
<rem:day>28</rem:day>
</rem:date>
</rem:version>
<rem:authors stakeholders ="STK-0001 "/>
<rem:comments>
Campos de usuario,contraseña,datos de contacto,dirección.</rem:comments>
<rem:importance value = "IMV-0002"/>
<rem:urgency value = "URV-0003"/>
<rem:status value = "STV-0003"/>
<rem:stability value = "SBV-0003"/>
<rem:triggeringEvent>
cuando la empresa desee actualizar alguno de sus datos</rem:triggeringEvent>
<rem:precondition>
Estar registrado en el sistema.<br/>Haber iniciado sesión.</rem:precondition>
<rem:postcondition>
La empresa actualizará sus datos</rem:postcondition>
<rem:frequency>
<rem:value>
10
</rem:value>
<rem:timeUnit value = "TUV-0008"/>
</rem:frequency>
<rem:step oid = "STP-0112">
<rem:number>1</rem:number>
<rem:useCaseAction useCase = "UC-0006"/><rem:stepException oid = "STX-0036">
<rem:condition>
algún campo esta vacío</rem:condition>
<rem:systemAction>
<rem:description>
mostrará un mensaje de error</rem:description>
</rem:systemAction>
<rem:termination value = "TEV-0002"/>
<rem:comments>
regresa al paso 1</rem:comments>
</rem:stepException>
<rem:comments>
Ninguno</rem:comments>
</rem:step>
</rem:useCase>
<rem:useCase
 oid = "UC-0027">
<rem:name>
Seleccionar fecha expiración</rem:name>
<rem:version>
<rem:major>1</rem:major>
<rem:minor>0</rem:minor>
<rem:date>
<rem:year>2016</rem:year>
<rem:month>2</rem:month>
<rem:day>29</rem:day>
</rem:date>
</rem:version>
<rem:authors stakeholders ="STK-0001 "/>
<rem:comments>
Ninguno</rem:comments>
<rem:importance value = "IMV-0003"/>
<rem:urgency value = "URV-0003"/>
<rem:status value = "STV-0003"/>
<rem:stability value = "SBV-0003"/>
<rem:triggeringEvent>
la empresa esté por  publicar alguna vacante de empleo</rem:triggeringEvent>
<rem:precondition>
Seleccionar el apartado publicar vacante</rem:precondition>
<rem:postcondition>
Se determinará una fecha para que la vacante desaparezca</rem:postcondition>
<rem:frequency>
<rem:value>
1
</rem:value>
<rem:timeUnit value = "TUV-0009"/>
</rem:frequency>
<rem:step oid = "STP-0113">
<rem:number>1</rem:number>
<rem:actorAction actor = "ACT-0002">
<rem:description>
seleccionará la fecha de inicio de la publicación</rem:description>
</rem:actorAction>
<rem:comments>
Ninguno</rem:comments>
</rem:step>
<rem:step oid = "STP-0114">
<rem:number>2</rem:number>
<rem:systemAction>
<rem:description>
verificará que la fecha de inicio no sea previa a la fecha en que se está publicando</rem:description>
</rem:systemAction>
<rem:stepException oid = "STX-0037">
<rem:condition>
la fecha de inicio es menor a la fecha actual</rem:condition>
<rem:systemAction>
<rem:description>
mostrará un mensaje de error</rem:description>
</rem:systemAction>
<rem:termination value = "TEV-0002"/>
<rem:comments>
regresa al paso 1</rem:comments>
</rem:stepException>
<rem:comments>
Ninguno</rem:comments>
</rem:step>
<rem:step oid = "STP-0115">
<rem:number>3</rem:number>
<rem:actorAction actor = "ACT-0002">
<rem:description>
seleccionará la fecha en que la publicación de la vacante desaparecerá del sistema</rem:description>
</rem:actorAction>
<rem:comments>
Ninguno</rem:comments>
</rem:step>
<rem:step oid = "STP-0116">
<rem:number>4</rem:number>
<rem:systemAction>
<rem:description>
verificará que la fecha de fin no sea mayor a un mes con respecto a la fecha en que se está publicando</rem:description>
</rem:systemAction>
<rem:stepException oid = "STX-0038">
<rem:condition>
si la fecha de inicio y fin es mayor a un mes</rem:condition>
<rem:systemAction>
<rem:description>
el sistema mostrará un mensaje de error</rem:description>
</rem:systemAction>
<rem:termination value = "TEV-0002"/>
<rem:comments>
regresa al paso 3</rem:comments>
</rem:stepException>
<rem:comments>
Ninguno</rem:comments>
</rem:step>
</rem:useCase>
<rem:useCase
 oid = "UC-0028">
<rem:name>
Validar número candidatos</rem:name>
<rem:version>
<rem:major>1</rem:major>
<rem:minor>0</rem:minor>
<rem:date>
<rem:year>2016</rem:year>
<rem:month>2</rem:month>
<rem:day>29</rem:day>
</rem:date>
</rem:version>
<rem:authors stakeholders ="STK-0001 "/>
<rem:comments>
Ninguno</rem:comments>
<rem:importance value = "IMV-0002"/>
<rem:urgency value = "URV-0003"/>
<rem:status value = "STV-0003"/>
<rem:stability value = "SBV-0003"/>
<rem:triggeringEvent>
la empresa desee dar de alta la publicación de una vacante y va asignar un número de candidatos máximo para la vacante</rem:triggeringEvent>
<rem:precondition>
Seleccionar el apartado publicar vacante</rem:precondition>
<rem:postcondition>
El número de candidatos será seleccionado</rem:postcondition>
<rem:frequency>
<rem:value>
1
</rem:value>
<rem:timeUnit value = "TUV-0010"/>
</rem:frequency>
<rem:step oid = "STP-0117">
<rem:number>1</rem:number>
<rem:actorAction actor = "ACT-0002">
<rem:description>
seleccionará el numero de candidatos a aplicar para la vacante de empleo</rem:description>
</rem:actorAction>
<rem:comments>
Ninguno</rem:comments>
</rem:step>
<rem:step oid = "STP-0118">
<rem:number>2</rem:number>
<rem:systemAction>
<rem:description>
verificar que el numero de candidatos que puedan postularse no sea mayor a 20</rem:description>
</rem:systemAction>
<rem:stepException oid = "STX-0039">
<rem:condition>
el número de candidatos es mayor a 50</rem:condition>
<rem:systemAction>
<rem:description>
el sistema mostrará un mensaje de error</rem:description>
</rem:systemAction>
<rem:termination value = "TEV-0002"/>
<rem:comments>
regresa al paso 1</rem:comments>
</rem:stepException>
<rem:comments>
Ninguno</rem:comments>
</rem:step>
<rem:step oid = "STP-0119">
<rem:number>3</rem:number>
<rem:systemAction>
<rem:description>
guardará el número de candidatos</rem:description>
</rem:systemAction>
<rem:comments>
Ninguno</rem:comments>
</rem:step>
</rem:useCase>
<rem:useCase
 oid = "UC-0029">
<rem:name>
Buscar</rem:name>
<rem:version>
<rem:major>1</rem:major>
<rem:minor>0</rem:minor>
<rem:date>
<rem:year>2016</rem:year>
<rem:month>2</rem:month>
<rem:day>29</rem:day>
</rem:date>
</rem:version>
<rem:authors stakeholders ="STK-0001 "/>
<rem:comments>
Ninguno</rem:comments>
<rem:importance value = "IMV-0004"/>
<rem:urgency value = "URV-0003"/>
<rem:status value = "STV-0003"/>
<rem:stability value = "SBV-0003"/>
<rem:triggeringEvent>
el usuario persona desempleada desee buscar una empresa o una vacante por área</rem:triggeringEvent>
<rem:precondition>
Haber iniciado sesión</rem:precondition>
<rem:postcondition>
El usuario encontrará una vacante de acuerdo a su tipo de búsqueda</rem:postcondition>
<rem:frequency>
<rem:value>
5
</rem:value>
<rem:timeUnit value = "TUV-0009"/>
</rem:frequency>
<rem:step oid = "STP-0121">
<rem:number>1</rem:number>
<rem:actorAction actor = "ACT-0001">
<rem:description>
localizará el recuadro dónde estará el buscador</rem:description>
</rem:actorAction>
<rem:comments>
Ninguno</rem:comments>
</rem:step>
<rem:step oid = "STP-0120">
<rem:number>2</rem:number>
<rem:actorAction actor = "ACT-0001">
<rem:description>
escribirá el nombre de una empresa o área de la cual desea </rem:description>
</rem:actorAction>
<rem:stepException oid = "STX-0040">
<rem:condition>
la persona desempleada no escribe nada y presiona buscar</rem:condition>
<rem:systemAction>
<rem:description>
mostrará un mensaje de error </rem:description>
</rem:systemAction>
<rem:termination value = "TEV-0002"/>
<rem:comments>
Ninguno</rem:comments>
</rem:stepException>
<rem:comments>
Ninguno</rem:comments>
</rem:step>
<rem:step oid = "STP-0122">
<rem:number>3</rem:number>
<rem:systemAction>
<rem:description>
mostrará los resultados de la búsqueda</rem:description>
</rem:systemAction>
<rem:comments>
Ninguno</rem:comments>
</rem:step>
</rem:useCase>
<rem:useCase
 oid = "UC-0030">
<rem:name>
Validar campos vacíos publicar vacante</rem:name>
<rem:version>
<rem:major>1</rem:major>
<rem:minor>0</rem:minor>
<rem:date>
<rem:year>2016</rem:year>
<rem:month>3</rem:month>
<rem:day>1</rem:day>
</rem:date>
</rem:version>
<rem:authors stakeholders ="STK-0001 "/>
<rem:comments>
Ninguno</rem:comments>
<rem:importance value = "IMV-0002"/>
<rem:urgency value = "URV-0003"/>
<rem:status value = "STV-0003"/>
<rem:stability value = "SBV-0002"/>
<rem:triggeringEvent>
cuando el actor empresa vaya a publicar una vacante se encuentra con campos como son descripción del puesto,nombre,salario y horario, entonces se deben validar que todos los campos sean llenados</rem:triggeringEvent>
<rem:precondition>
Seleccionar la opción publicar vacante</rem:precondition>
<rem:postcondition>
Los campos serán llenados correctamente</rem:postcondition>
<rem:frequency>
<rem:value>
2
</rem:value>
<rem:timeUnit value = "TUV-0010"/>
</rem:frequency>
<rem:step oid = "STP-0123">
<rem:number>1</rem:number>
<rem:actorAction actor = "ACT-0002">
<rem:description>
escribirá el nombre del puesto,requisitos,salario,horario y breve descripción</rem:description>
</rem:actorAction>
<rem:comments>
Ninguno</rem:comments>
</rem:step>
<rem:step oid = "STP-0124">
<rem:number>2</rem:number>
<rem:systemAction>
<rem:description>
verifica todos que los campos sean llenados</rem:description>
</rem:systemAction>
<rem:stepException oid = "STX-0042">
<rem:condition>
faltó algún campo por llenar</rem:condition>
<rem:systemAction>
<rem:description>
mostrará un mensaje de error</rem:description>
</rem:systemAction>
<rem:termination value = "TEV-0002"/>
<rem:comments>
regresa al paso 1</rem:comments>
</rem:stepException>
<rem:comments>
Ninguno</rem:comments>
</rem:step>
<rem:step oid = "STP-0125">
<rem:number>3</rem:number>
<rem:systemAction>
<rem:description>
verifica que los campos sean llenados con el tipo de dato correcto</rem:description>
</rem:systemAction>
<rem:stepException oid = "STX-0043">
<rem:condition>
se llenó algún campo con tipo de dato incorrecto</rem:condition>
<rem:systemAction>
<rem:description>
mostrará un mensaje de error</rem:description>
</rem:systemAction>
<rem:termination value = "TEV-0002"/>
<rem:comments>
Ninguno</rem:comments>
</rem:stepException>
<rem:comments>
Ninguno</rem:comments>
</rem:step>
</rem:useCase>
</rem:c_requirementsSpecification>
<rem:d_requirementsSpecification oid = "DRS-0002">
<rem:name>Documento de Análisis del Sistema</rem:name>
<rem:version>
<rem:major>1</rem:major>
<rem:minor>0</rem:minor>
<rem:date>
<rem:year>2016</rem:year>
<rem:month>2</rem:month>
<rem:day>20</rem:day>
</rem:date>
</rem:version>
<rem:comments>
Ninguno
</rem:comments>
</rem:d_requirementsSpecification>
<rem:defectsSpecification oid = "DFS-0003">
<rem:name>Registro de Conflictos y Defectos</rem:name>
<rem:version>
<rem:major>1</rem:major>
<rem:minor>0</rem:minor>
<rem:date>
<rem:year>2016</rem:year>
<rem:month>2</rem:month>
<rem:day>20</rem:day>
</rem:date>
</rem:version>
<rem:comments>
Ninguno
</rem:comments>
</rem:defectsSpecification>
<rem:changeRequestsSpecification oid = "CHS-0004">
<rem:name>Registro de Peticiones de Cambio</rem:name>
<rem:version>
<rem:major>1</rem:major>
<rem:minor>0</rem:minor>
<rem:date>
<rem:year>2016</rem:year>
<rem:month>2</rem:month>
<rem:day>20</rem:day>
</rem:date>
</rem:version>
<rem:comments>
Ninguno
</rem:comments>
</rem:changeRequestsSpecification>
<rem:trace source = "UC-0007"  target = "UC-0028" >
<rem:isChecked/>
</rem:trace>
<rem:trace source = "UC-0001"  target = "UC-0013" >
<rem:isChecked/>
</rem:trace>
<rem:trace source = "UC-0001"  target = "UC-0011" >
<rem:isChecked/>
</rem:trace>
<rem:trace source = "UC-0014"  target = "UC-0001" >
<rem:isChecked/>
</rem:trace>
<rem:trace source = "UC-0001"  target = "UC-0009" >
<rem:isChecked/>
</rem:trace>
<rem:trace source = "UC-0002"  target = "UC-0012" >
<rem:isChecked/>
</rem:trace>
<rem:trace source = "UC-0002"  target = "UC-0010" >
<rem:isChecked/>
</rem:trace>
<rem:trace source = "UC-0014"  target = "UC-0002" >
<rem:isChecked/>
</rem:trace>
<rem:trace source = "UC-0002"  target = "UC-0013" >
<rem:isChecked/>
</rem:trace>
<rem:trace source = "UC-0003"  target = "UC-0019" >
<rem:isChecked/>
</rem:trace>
<rem:trace source = "UC-0003"  target = "UC-0020" >
<rem:isChecked/>
</rem:trace>
<rem:trace source = "UC-0022"  target = "UC-0004" >
<rem:isChecked/>
</rem:trace>
<rem:trace source = "UC-0016"  target = "UC-0003" >
<rem:isChecked/>
</rem:trace>
<rem:trace source = "UC-0004"  target = "UC-0019" >
<rem:isChecked/>
</rem:trace>
<rem:trace source = "UC-0004"  target = "UC-0020" >
<rem:isChecked/>
</rem:trace>
<rem:trace source = "UC-0004"  target = "UC-0023" >
<rem:isChecked/>
</rem:trace>
<rem:trace source = "UC-0004"  target = "UC-0024" >
<rem:isChecked/>
</rem:trace>
<rem:trace source = "UC-0007"  target = "UC-0030" >
<rem:isChecked/>
</rem:trace>
<rem:trace source = "UC-0005"  target = "UC-0001" >
<rem:isChecked/>
</rem:trace>
<rem:trace source = "UC-0005"  target = "UC-0003" >
<rem:isChecked/>
</rem:trace>
<rem:trace source = "UC-0021"  target = "UC-0003" >
<rem:isChecked/>
</rem:trace>
<rem:trace source = "UC-0005"  target = "UC-0025" >
<rem:isChecked/>
</rem:trace>
<rem:trace source = "UC-0006"  target = "UC-0026" >
<rem:isChecked/>
</rem:trace>
<rem:trace source = "UC-0007"  target = "UC-0027" >
<rem:isChecked/>
</rem:trace>
<rem:trace source = "UC-0003"  target = "UC-0018" >
<rem:isChecked/>
</rem:trace>
<rem:trace source = "UC-0015"  target = "UC-0003" >
<rem:isChecked/>
</rem:trace>
<rem:trace source = "UC-0003"  target = "UC-0017" >
<rem:isChecked/>
</rem:trace>
<rem:trace source = "UC-0006"  target = "UC-0002" >
<rem:isChecked/>
</rem:trace>
<rem:trace source = "UC-0006"  target = "UC-0004" >
<rem:isChecked/>
</rem:trace>
<rem:trace source = "UC-0016"  target = "UC-0004" >
<rem:isChecked/>
</rem:trace>
<rem:predefinedValueTypes>
<rem:predefinedValueType
 oid = "PVT-0003">
<rem:name>
Natural</rem:name>
<rem:version>
<rem:major>1</rem:major>
<rem:minor>0</rem:minor>
<rem:date>
<rem:year>2000</rem:year>
<rem:month>10</rem:month>
<rem:day>30</rem:day>
</rem:date>
</rem:version>
<rem:comments>
Predefined OCL type</rem:comments>
<rem:description>
Natural numbers</rem:description>
<rem:definition>
(null)
</rem:definition>
</rem:predefinedValueType>
<rem:predefinedValueType
 oid = "PVT-0004">
<rem:name>
String</rem:name>
<rem:version>
<rem:major>1</rem:major>
<rem:minor>0</rem:minor>
<rem:date>
<rem:year>2000</rem:year>
<rem:month>10</rem:month>
<rem:day>30</rem:day>
</rem:date>
</rem:version>
<rem:comments>
Predefined OCL type</rem:comments>
<rem:description>
Alphanumeric strings</rem:description>
<rem:definition>
(null)
</rem:definition>
</rem:predefinedValueType>
<rem:predefinedValueType
 oid = "PVT-0001">
<rem:name>
Real</rem:name>
<rem:version>
<rem:major>1</rem:major>
<rem:minor>0</rem:minor>
<rem:date>
<rem:year>2000</rem:year>
<rem:month>10</rem:month>
<rem:day>30</rem:day>
</rem:date>
</rem:version>
<rem:comments>
Predefined OCL type</rem:comments>
<rem:description>
Real numbers</rem:description>
<rem:definition>
(null)
</rem:definition>
</rem:predefinedValueType>
<rem:predefinedValueType
 oid = "PVT-0002">
<rem:name>
Integer</rem:name>
<rem:version>
<rem:major>1</rem:major>
<rem:minor>0</rem:minor>
<rem:date>
<rem:year>2000</rem:year>
<rem:month>10</rem:month>
<rem:day>30</rem:day>
</rem:date>
</rem:version>
<rem:comments>
Predefined OCL type</rem:comments>
<rem:description>
Integer numbers</rem:description>
<rem:definition>
(null)
</rem:definition>
</rem:predefinedValueType>
<rem:predefinedValueType
 oid = "PVT-0005">
<rem:name>
Date</rem:name>
<rem:version>
<rem:major>1</rem:major>
<rem:minor>0</rem:minor>
<rem:date>
<rem:year>2000</rem:year>
<rem:month>10</rem:month>
<rem:day>30</rem:day>
</rem:date>
</rem:version>
<rem:comments>
Predefined OCL type (non-standard)</rem:comments>
<rem:description>
Dates</rem:description>
<rem:definition>
(null)
</rem:definition>
</rem:predefinedValueType>
<rem:predefinedValueType
 oid = "PVT-0006">
<rem:name>
Time</rem:name>
<rem:version>
<rem:major>1</rem:major>
<rem:minor>0</rem:minor>
<rem:date>
<rem:year>2000</rem:year>
<rem:month>10</rem:month>
<rem:day>30</rem:day>
</rem:date>
</rem:version>
<rem:comments>
Predefined OCL type (non-standard)</rem:comments>
<rem:description>
Hour:minutes:seconds</rem:description>
<rem:definition>
(null)
</rem:definition>
</rem:predefinedValueType>
</rem:predefinedValueTypes>
<rem:predefinedValues>
<rem:changeRequestStatusValue oid = "CRV-0001">
<rem:name>PD</rem:name>
</rem:changeRequestStatusValue>
<rem:changeRequestStatusValue oid = "CRV-0002">
<rem:name>pendiente de análisis</rem:name>
</rem:changeRequestStatusValue>
<rem:changeRequestStatusValue oid = "CRV-0003">
<rem:name>pendiente de aprobar/rechazar</rem:name>
</rem:changeRequestStatusValue>
<rem:changeRequestStatusValue oid = "CRV-0004">
<rem:name>pendiente de realización</rem:name>
</rem:changeRequestStatusValue>
<rem:changeRequestStatusValue oid = "CRV-0005">
<rem:name>verificado</rem:name>
</rem:changeRequestStatusValue>
<rem:changeRequestStatusValue oid = "CRV-0006">
<rem:name>rechazado</rem:name>
</rem:changeRequestStatusValue>
<rem:conflictStatusValue oid = "CSV-0001">
<rem:name>PD</rem:name>
</rem:conflictStatusValue>
<rem:conflictStatusValue oid = "CSV-0002">
<rem:name>no resuelto</rem:name>
</rem:conflictStatusValue>
<rem:conflictStatusValue oid = "CSV-0003">
<rem:name>en proceso de negociación</rem:name>
</rem:conflictStatusValue>
<rem:conflictStatusValue oid = "CSV-0004">
<rem:name>resuelto</rem:name>
</rem:conflictStatusValue>
<rem:defectStatusValue oid = "DSV-0001">
<rem:name>PD</rem:name>
</rem:defectStatusValue>
<rem:defectStatusValue oid = "DSV-0002">
<rem:name>no eliminado</rem:name>
</rem:defectStatusValue>
<rem:defectStatusValue oid = "DSV-0003">
<rem:name>en proceso de negociación</rem:name>
</rem:defectStatusValue>
<rem:defectStatusValue oid = "DSV-0004">
<rem:name>eliminado</rem:name>
</rem:defectStatusValue>
<rem:defectTypeValue oid = "DTV-0013">
<rem:name>Prioridad no establecida</rem:name>
<rem:description>
<![CDATA[El requisito o requisitos no tienen establecida su prioridad, es decir, su importancia y su urgencia]]>
</rem:description>
</rem:defectTypeValue>
<rem:defectTypeValue oid = "DTV-0005">
<rem:name>No verificabilidad</rem:name>
<rem:description>
<![CDATA[No se puede comprobar que el sistema satisface el requisito o requisitos]]>
</rem:description>
</rem:defectTypeValue>
<rem:defectTypeValue oid = "DTV-0004">
<rem:name>Incomprensibilidad</rem:name>
<rem:description>
<![CDATA[El requisito o requisitos no pueden ser entendidos por algún lector]]>
</rem:description>
</rem:defectTypeValue>
<rem:defectTypeValue oid = "DTV-0003">
<rem:name>No necesidad</rem:name>
<rem:description>
<![CDATA[El requisito o requisitos no son necesarios porque no contribuyen a satisfacer ninguna necesidad de clientes o usuarios]]>
</rem:description>
</rem:defectTypeValue>
<rem:defectTypeValue oid = "DTV-0007">
<rem:name>No implementabilidad</rem:name>
<rem:description>
<![CDATA[El requisito o requisitos no pueden ser implementados con la tecnología actual o dentro de un coste razonable]]>
</rem:description>
</rem:defectTypeValue>
<rem:defectTypeValue oid = "DTV-0006">
<rem:name>Inconsistencia</rem:name>
<rem:description>
<![CDATA[El requisito o requisitos no son consistentes, es decir, presentan contradicciones internas o entre varios]]>
</rem:description>
</rem:defectTypeValue>
<rem:defectTypeValue oid = "DTV-0008">
<rem:name>Verbosidad excesiva</rem:name>
<rem:description>
<![CDATA[El requisito o requisitos pueden expresarse de forma más concisa sin alterar su significado]]>
</rem:description>
</rem:defectTypeValue>
<rem:defectTypeValue oid = "DTV-0002">
<rem:name>Ambigüedad</rem:name>
<rem:description>
<![CDATA[El requisito o requisitos, aunque comprensibles, tienen más de una interpretación posible]]>
</rem:description>
</rem:defectTypeValue>
<rem:defectTypeValue oid = "DTV-0001">
<rem:name>PD</rem:name>
<rem:description>
<![CDATA[Por Determinar]]>
</rem:description>
</rem:defectTypeValue>
<rem:defectTypeValue oid = "DTV-0012">
<rem:name>Incompleción</rem:name>
<rem:description>
<![CDATA[El requisito o requisitos no describen todo lo que el sistema se supone que deberá hacer, no describen las respuestas del sistema a todas las posibles situaciones o incluyen elementos por determinar (PD)]]>
</rem:description>
</rem:defectTypeValue>
<rem:defectTypeValue oid = "DTV-0011">
<rem:name>Imprecisión</rem:name>
<rem:description>
<![CDATA[El requisito o requisitos no se expresan de forma precisa, es decir, usando cantidades numéricas siempre que sea posible con el nivel adecuado de precisión]]>
</rem:description>
</rem:defectTypeValue>
<rem:defectTypeValue oid = "DTV-0010">
<rem:name>Redundancia</rem:name>
<rem:description>
<![CDATA[El requisito o requisitos son redundantes o contienen elementos redundantes]]>
</rem:description>
</rem:defectTypeValue>
<rem:defectTypeValue oid = "DTV-0009">
<rem:name>Dependiente del diseño</rem:name>
<rem:description>
<![CDATA[El requisito o requisitos incluyen elementos dependientes del diseño del sistema]]>
</rem:description>
</rem:defectTypeValue>
<rem:defectTypeValue oid = "DTV-0014">
<rem:name>Estabilidad no establecida</rem:name>
<rem:description>
<![CDATA[El requisito o requisitos no tienen estimada su estabilidad]]>
</rem:description>
</rem:defectTypeValue>
<rem:defectTypeValue oid = "DTV-0015">
<rem:name>Nivel incorrecto de detalle</rem:name>
<rem:description>
<![CDATA[El requisito o requisitos no están expresados con el nivel adecuado de detalle, es decir, son demasiado abstractos o demasiado detallados]]>
</rem:description>
</rem:defectTypeValue>
<rem:defectTypeValue oid = "DTV-0016">
<rem:name>No rastreabilidad</rem:name>
<rem:description>
<![CDATA[El requisito o requisitos no están trazados hacia sus orígenes, bien requisitos de nivel superior (objetivos), bien clientes y usuarios]]>
</rem:description>
</rem:defectTypeValue>
<rem:defectTypeValue oid = "DTV-0017">
<rem:name>Organización incorrecta</rem:name>
<rem:description>
<![CDATA[El requisito o requisitos no están organizados correctamente según la normativa aplicada o el documento no contiene las secciones obligatorias]]>
</rem:description>
</rem:defectTypeValue>
<rem:defectTypeValue oid = "DTV-0023">
<rem:name>Otro</rem:name>
<rem:description>
<![CDATA[El requisito o requisitos presentan otro tipo de defecto]]>
</rem:description>
</rem:defectTypeValue>
<rem:importanceValue oid = "IMV-0001">
<rem:name>PD</rem:name>
</rem:importanceValue>
<rem:importanceValue oid = "IMV-0002">
<rem:name>vital</rem:name>
</rem:importanceValue>
<rem:importanceValue oid = "IMV-0003">
<rem:name>importante</rem:name>
</rem:importanceValue>
<rem:importanceValue oid = "IMV-0004">
<rem:name>quedaría bien</rem:name>
</rem:importanceValue>
<rem:stabilityValue oid = "SBV-0001">
<rem:name>PD</rem:name>
</rem:stabilityValue>
<rem:stabilityValue oid = "SBV-0002">
<rem:name>baja</rem:name>
</rem:stabilityValue>
<rem:stabilityValue oid = "SBV-0003">
<rem:name>media</rem:name>
</rem:stabilityValue>
<rem:stabilityValue oid = "SBV-0004">
<rem:name>alta</rem:name>
</rem:stabilityValue>
<rem:statusValue oid = "STV-0001">
<rem:name>PD</rem:name>
</rem:statusValue>
<rem:statusValue oid = "STV-0002">
<rem:name>en construcción</rem:name>
</rem:statusValue>
<rem:statusValue oid = "STV-0003">
<rem:name>pendiente de verificación</rem:name>
</rem:statusValue>
<rem:statusValue oid = "STV-0004">
<rem:name>pendiente de validación</rem:name>
</rem:statusValue>
<rem:statusValue oid = "STV-0005">
<rem:name>validado</rem:name>
</rem:statusValue>
<rem:terminationValue oid = "TEV-0001">
<rem:name>PD</rem:name>
</rem:terminationValue>
<rem:terminationValue oid = "TEV-0002">
<rem:name>continúa</rem:name>
</rem:terminationValue>
<rem:terminationValue oid = "TEV-0003">
<rem:name>queda sin efecto</rem:name>
</rem:terminationValue>
<rem:timeUnitValue oid = "TUV-0001">
<rem:name>PD</rem:name>
</rem:timeUnitValue>
<rem:timeUnitValue oid = "TUV-0002">
<rem:name>año(s)</rem:name>
</rem:timeUnitValue>
<rem:timeUnitValue oid = "TUV-0005">
<rem:name>mes(es)</rem:name>
</rem:timeUnitValue>
<rem:timeUnitValue oid = "TUV-0007">
<rem:name>semana(s)</rem:name>
</rem:timeUnitValue>
<rem:timeUnitValue oid = "TUV-0008">
<rem:name>día(s)</rem:name>
</rem:timeUnitValue>
<rem:timeUnitValue oid = "TUV-0009">
<rem:name>hora(s)</rem:name>
</rem:timeUnitValue>
<rem:timeUnitValue oid = "TUV-0010">
<rem:name>minuto(s)</rem:name>
</rem:timeUnitValue>
<rem:timeUnitValue oid = "TUV-0011">
<rem:name>segundo(s)</rem:name>
</rem:timeUnitValue>
<rem:timeUnitValue oid = "TUV-0012">
<rem:name>décima(s) de segundo</rem:name>
</rem:timeUnitValue>
<rem:timeUnitValue oid = "TUV-0013">
<rem:name>centésima(s) de segundo</rem:name>
</rem:timeUnitValue>
<rem:timeUnitValue oid = "TUV-0014">
<rem:name>milisegundo(s)</rem:name>
</rem:timeUnitValue>
<rem:urgencyValue oid = "URV-0001">
<rem:name>PD</rem:name>
</rem:urgencyValue>
<rem:urgencyValue oid = "URV-0002">
<rem:name>inmediatamente</rem:name>
</rem:urgencyValue>
<rem:urgencyValue oid = "URV-0003">
<rem:name>hay presión</rem:name>
</rem:urgencyValue>
<rem:urgencyValue oid = "URV-0004">
<rem:name>puede esperar</rem:name>
</rem:urgencyValue>
</rem:predefinedValues>
</rem:requirementsProject>
